pyimkernel/__init__.py
pyimkernel/builtin_kernels.py
pyimkernel/main.py
pyimkernel-1.3.2.dist-info/LICENSE
pyimkernel-1.3.2.dist-info/METADATA
pyimkernel-1.3.2.dist-info/WHEEL
pyimkernel-1.3.2.dist-info/top_level.txt
pyimkernel-1.3.2.dist-info/RECORD
