Metadata-Version: 2.1
Name: pyimkernel
Version: 1.3.2
Summary: Applying some image kernel(s) on a grayscale or RGB|BGR color-scale image
Home-page: https://github.com/amirho3einsedaghati/pyimkernel
Author: Amir Hosein Sedaghati
Author-email: amirhosseinsedaghati42@gmail.com
License: MIT
Keywords: image kernels/filters,image preprocessing,Applying image kernels/filters on a grayscale or color scale image
Classifier: Development Status :: 5 - Production/Stable
Classifier: Environment :: Console
Classifier: Intended Audience :: Developers
Classifier: Intended Audience :: Education
Classifier: License :: OSI Approved :: MIT License
Classifier: Operating System :: MacOS
Classifier: Operating System :: Microsoft :: Windows
Classifier: Operating System :: POSIX
Classifier: Operating System :: Unix
Classifier: Programming Language :: Python :: 3 :: Only
Classifier: Programming Language :: Python :: 3.6
Classifier: Programming Language :: Python :: 3.7
Classifier: Programming Language :: Python :: 3.8
Classifier: Programming Language :: Python :: 3.9
Classifier: Programming Language :: Python :: 3.10
Classifier: Programming Language :: Python :: 3.11
Classifier: Topic :: Scientific/Engineering
License-File: LICENSE
Requires-Dist: numpy
Requires-Dist: matplotlib
Requires-Dist: opencv-python
Requires-Dist: pillow
Requires-Dist: pilgram2
